WrapperXSelector/WrapperXSelector.py
WrapperXSelector/__init__.py
WrapperXSelector/general_wrapper.js
WrapperXSelector/table_wrapper.js
WrapperXSelector/external_files/css/st.action-panel.css
WrapperXSelector/external_files/js/jquery-3.7.1.min.js
WrapperXSelector/external_files/js/st.action-panel.js
WrapperXSelector/external_files/js/sweetalert2.all.min.js
WrapperXSelector-0.1.39.dist-info/LICENSE
WrapperXSelector-0.1.39.dist-info/METADATA
WrapperXSelector-0.1.39.dist-info/WHEEL
WrapperXSelector-0.1.39.dist-info/top_level.txt
WrapperXSelector-0.1.39.dist-info/RECORD
